Metadata-Version: 1.0
Name: imageTable
Version: 0.1.1
Summary: manipulation of czi and ims files
Home-page: UNKNOWN
Author: UNKNOWN
Author-email: UNKNOWN
License: UNKNOWN
Platform: UNKNOWN
